Workbook
Name ИмяСтрахователя: Основной!$E$7
Name поиск1: OFFSET(перечень!$B$1,MATCH(Основной!$B$32,перечень!$B:$B,0)-1,1,COUNTIF(перечень!$B:$B,Основной!$B$32),1)

Sheet Основной
A2: Заявление-вопросник на страхование имущества
A4: 1. Просим Вас заполнить ВСЕ обязательные графы (отмечены звездочкой *) настоящего заявления-вопросника. Неполное заполнение заявления дает право СПАО "Ингосстрах" не принять заявление Страхователя и воздержаться от предоставления страхового покрытия, а неотвеченные вопросы приравниваются к ответу с наихудшим значением для целей определения параметров и стоимости страховой защиты. 2. Заявление-вопросник должно быть подписано руководителем или уполномоченным лицом Страхователя. 3. Просим Вас подписать и скрепить печатью каждую страницу.
A6: 1.1. | B6: Информация о Страхователе
B7: Наименование Страхователя:
B8: Юридический адрес:
B9: ИНН:
B10: Контактное лицо:
B11: Телефон: | F11: E-mail:
G12: Является способом взаимодействия со Страхователем.
A13: 1.2. | B13: Информация о Выгодоприобретателе Необходимо заполнить, если иное, чем Страхователь лицо.
B14: Наименование Выгодоприобретателя: | E14: ООО Сторук Воронеж
B15: Юридический адрес:
B16: ИНН: | E16: 3665806928
B17: На основании договора (залога/иное):
B18: № договора (залога/лизинга/иное): | G18: Действует с: | J18: по:
B19: Данные контактного лица (ФИО, должность, телефон/факс, e-mail):
A21: 1.3.* | B21: Укажите необходимый период страхования | F21: с: | I21: по:
A22: 1.4.* | B22: Информация о территории страхования Место расположения объектов страхования. Точный адрес. Если необходимо, с указанием номера корпуса, офиса и т.д.
B23: Страна: | I23: Индекс:
B24: Область/субъект:
B25: Район:
B26: Населенный пункт:
B27: Улица:
B28: Дом: | F28: Корпус: | I28: Строение:
B29: Дополнительно:
A30: 2. | B30: Информация об объектах страхования, страховых суммах, страховых рисках
A31: 2.1.* | B31: 2.1.1. Выберите основное назначение заявляемого на страхование имущества:
B33: 2.1.2. Выберите категорию:
A35: 2.2. | B35: Дайте краткое описание имущества, заявляемого на страхование:
A37: 2.3.* | B37: Укажите валюту, в которой выражена стоимость имущества:
A39: 2.4.* | B39: Укажите, на базе какой стоимости установлена страховая сумма:
B42: Включен ли в страховую сумму НДС?
A44: 2.5.* | B44: Выберите и укажите только те объекты, которые необходимо застраховать, укажите их страховую сумму. По возможности, приложите к заявлению перечень заявляемого на страхование имущества. Если выбрано страхование "по первому риску", укажите так же их страховую стоимость.
B45: Вид объекта, заявляемого на страхование: | H45: Страховая сумма: * | J45: Страховая стоимость:
B46: Здание или часть здания (конструктивные элементы, внутренняя и внешняя отделка).
B47: Здание или часть здания (конструктивные элементы, инженерные коммуникации), исключая отделку.
B48: Внешняя отделка здания или части здания, исключая дополнительные надстройки и оборудование.
B49: Внутренняя отделка помещений.
B50: Внешние сооружения и результаты работ по благоустройству территории страхования (ограды, шлагбаумы, рекламные щиты и вывески и т.п.).
B51: Оконные стекла, витрины, стеклопакеты, стеклянные элементы входных групп, дверей (если страхуются отдельной суммой).
B52: Различное оборудование, не являющееся конструктивной частью здания, а именно: технологическое, офисное, электронное, электробытовое оборудование, включая дополнительно установленное Страхователем оборудование систем вентиляции и кондиционирования.
B53: Мебель, инструмент, инвентарь.
B54: Товарные запасы готовой продукции (продовольственные и непродовольственные товары), запасы сырья и материалов. Укажите категорию ТМЦ. Если несколько типов ТМЦ, укажите наибольшую по сумме. | H54: Страховая сумма: | J54: Стоимость максимальных остатков ТМЦ:
B56: Дайте краткую характеристику/иную информацию по ТМЦ:
B58: Наличные деньги в кассовых аппаратах и сейфовых комнатах, за исключением наличных денег, хранящихся в банках и банкоматах. | J58: Для наличных денег не указывается.
B59: Иное (укажите):
B60: Справочно, страховая сумма итого: | H60: =H59+H58+H55+H53+H52+H51+H50+H49+H48+H47+H46 -> 0
B61: Страхование дополнительных расходов. При необходимости укажите требуемый лимит возмещения.
B62: Вид дополнительных расходов: | J62: Лимит возмещения:
B63: Расходы на расчистку (удаление обломков и вывоз мусора, демонтаж или снос части, или частей застрахованного имущества, которые были утрачены или повреждены в результате страхового случая)
B64: Расходы на защиту, сохранение и обеспечение безопасности (расходы на ограждение, укрепление и охрану застрахованного имущества)
B65: Расходы на ускоренное восстановление (расходы на оплату сверхурочных работ, работ в ночное время, в официальные праздники и выходные дни, оплату срочной доставки грузов (включая доставку воздушным транспортом))
B66: Расходы на урегулирование страхового случая (расходы на проведение экспертизы с целью установления причин, обстоятельств и/или размера убытков, привлекаемых сюрвейеров, лосс-аджастеров, других экспертов по урегулированию убытков)
B67: Расходы на экспертов (расходы на оплату услуг архитекторов, проектировщиков, аудиторов, инженеров и иных экспертов (специалистов)).
B68: Расходы, связанные с изменением норм и правил (расходы на приведение пострадавшего застрахованного имущества в соответствие с действующими новым строительным нормам и правилам, расходы по адаптации неповреждённой части застрахованного имущества для обеспечения возможности дальнейшего её использования с той частью застрахованного имущества, которая должна восстановлена)
B69: Расходы на восстановление документации (планов, чертежей, договоров, бухгалтерских записей и утраченных или поврежденных электронных данных при условии наличия их дубликатов)
B70: Расходы на временный переезд на период восстановительных работ: (расходы по вывозу (перемещению) имущества из поврежденного строения; расходы, связанные с передачей имущества на временное хранение; расходы на оборудование временно занимаемых помещений и арендную плату за их использование)
B71: Иные расходы (укажите):
A72: 2.6.* | B72: Выберите необходимый объем страхового покрытия:
B74: или
B75: Дополнительные риски: | J75: Лимит возмещения:
A78: 3. | B78: Информация о характеристиках и рискозащищенности объектов страхования
A79: 3.1. | B79: Функциональное назначение здания: | I79: Занимаемый этаж: | K79: 1-2
B80: Помещение в собственности или арендуемое?
B81: Год постройки или последнего капитального ремонта:
B82: Общая площадь здания (кв.м): | G82: Занимаемая площадь (кв.м):
B83: Здание: отдельностоящее или примыкающее?
B84: Окончены ли строительные/ремонтные/отделочные работы? Если ведутся, то укажите строящиеся объекты и/или помещения.
B86: Применяются ли при осуществлении деятельности предприятия огне- и/или взрывоопасные вещества, материалы, технологии? Если применяются, то укажите краткую характеристику.
B88: Есть ли в здании баня/сауна?
B89: Укажите материалы основных элементов здания. *
B90: Стены (капитальные, несущие):
B92: Перекрытия (несущие конструкции):
B94: Кровля (крыша):
B96: Наличие в здании котельной:
B97: На территории страхования используется газ?
A98: 3.2. | B98: Системы и средства пожарной защиты и охраны. *
B99: Наличие исправной автоматической системы пожарной сигнализации:
B100: Процент охвата помещений извещателями:
B101: Установлены ли работающие системы автоматического пожаротушения?
B102: Заключен ли договор на обслуживание системы пожаротушения?
B103: Оснащено ли здание огнетушителями в соответствии с нормами?
B104: Имеет ли предприятие действующие предписания со стороны органов пожарного надзора? Если есть, предоставьте копию предписаний.
B105: Установлена ли исправная охранная сигнализация?
B106: Средства пассивной защиты.
B107: Имущество расположено:
B108: Решетки/жалюзи на окнах:
B109: Наличие сплошного ограждения территории (забора):
B110: Круглосуточная физическая охрана объектов:
... B113: Наличие видеокамер по периметру здания/закрытого периметра:
A114: 4. | B114: Информация о повреждении имущества за последние 5 лет Просим указать все случаи повреждения имущества (убытки) за последние 5 лет. В случае, если количество убытков превышает количество строк в данном разделе заявления-вопросника, просим приложить информацию об убытках на дополнительном листе.
B115: Дата убытка: | D115: Характер убытка: | I115: Сумма ущерба, рублей:
B120: Просим Вас сообщить дополнительную информацию, которую Вы считаете необходимым указать, и которая не нашла своего отражения выше:
B123: Подписывая настоящее заявление – вопросник, Страхователь подтверждает достоверность и правдивость указанных в нем сведений.
B124: При заключении договора страхования, Страховщик полагается на заверения, данные Страхователем в Заявлении-вопроснике или в ответах на письменные запросы Страховщика. В случае, если будет установлено, что заверения Страхователя не соответствуют действительности, Страховщик вправе применить последствия, предусмотренные ст. 431.2, 944 ГК РФ. При заключении договора страхования Страхователь (Выгодоприобретатель) должен уведомить Страховщика об известных ему дефектах и недостатках передаваемого на страхование имущества. Не является страховым случаем возникновение ущерба (убытка) вследствие дефектов и недостатков застрахованного имущества, уже имевшихся на дату заключения договора страхования, о которых Страховщик не был уведомлен Страхователем при заключении договора страхования.
B125: При необходимости страхования объектов и/или рисков, указанных ниже, просьба отметить их и заполнить дополнительную информацию.
B127: При выборе пунктов ниже, заполните дополнительные листы с заявлением:
B128: • MB - Поломки машин и оборудования.
B129: • BI - Убытки от перерыва в производственной (коммерческой) деятельности.
B130: • EE - Электрические поломки оборудования.
...

Sheet MB
A1: Дополнительное заявление на страхование "Поломки машин и оборудования"
A3: 1. | B3: Укажите общую страховую сумму заявляемых на страхование от поломок машин и оборудования. Если на основном листе было выбрано страхование "по первому риску", укажите так же общую страховую стоимость.
B4: Страховая сумма: | G4: Страховая стоимость:
A5: 2. | B5: Выберите необходимый объем страхового покрытия: *
A7: 3. | B7: Приложите к заявлению перечень заявляемых на страхование машин и оборудования по форме, приведенной ниже.
B9: № п/п | C9: Наименование объекта, заявляемого на страхование: | F9: Год выпуска: | G9: Страховая сумма: | I9: Страховая стоимость:
B10: 1
B11: …

Sheet BI
A1: Дополнительное заявление на страхование "Убытки от перерыва в производственной (комерческой) деятельности"
A3: 1. | B3: Укажите необходимый период (в месяцах) возмещения:
A4: 2. | B4: Объекты страхования/статьи расходов: | J4: Страховая сумма:
B5: Заработная плата рабочих и служащих Страхователя
B6: Платежи органам социального страхования и аналогичные им платежи
B7: Плата за аренду помещений, оборудования или иного арендуемого имущества
B8: Налоги и сборы, подлежащие оплате вне зависимости от оборота и результатов хозяйственной деятельности
B9: Проценты по кредитам или иным привлеченным средствам
B10: Амортизационные отчисления по нормам, установленным для предприятия Страхователя
B11: Сумма чистой прибыли (прибыли после налогообложения)
B12: Сумма поступлений арендных платежей (платежей от сдачи в аренду помещений)
B13: Свой вариант 1 (указать наименование)
B14: Свой вариант 2 (указать наименование)
B15: Справочно, страховая сумма итого: | J15: =J5+J6+J7+J8+J9+J10+J11+J12+J13+J14 -> 0
A16: 3. | B16: Расширения страхового покрытия (CBI):

Sheet EE
A1: Дополнительное заявление на страхование "Электрические поломки оборудования"
A3: 1. | B3: Укажите общую страховую сумму заявляемого на страхование от электрических поломок оборудования. Если на основном листе было выбрано страхование "по первому риску", укажите так же общую страховую стоимость.
B4: Страховая сумма: | G4: Страховая стоимость:
A5: 2. | B5: Выберите необходимый объем страхового покрытия: *
A7: 3. | B7: Приложите к заявлению перечень заявляемого на страхование оборудования по форме, приведенной ниже.
B9: № п/п | C9: Наименование объекта, заявляемого на страхование: | F9: Год выпуска: | G9: Страховая сумма: | I9: Страховая стоимость:
B10: 1
B11: …

Sheet Авто
A1: Дополнительное заявление на страхование "Автомобили на стоянках, в помещениях автосервисов и автодилеров"
A3: 1. | B3: 1.1. Где и как хранятся документы на машины?
B4: 1.2. Где и как хранятся ключи на машины?
B5: 1.3. Сколько бензина залито (л)?
A6: 2. | B6: При наличии открытой стоянки.
B7: 2.1. Количество въездов/выездов:
B8: 2.2. Высота ограждения (м):
B9: 2.3. Порядок въезда и выезда:
B10: 2.4. Эксплуатация стоянки только страхователем или нет?
B11: 2.5. Наличие видеокамер, контролирующих свыше 80% территории:
B12: 2.6. Наличие сторожевых собак:
B13: 2.7. Обход территории:
B14: 2.8. Находятся ли автомобиле в прямой видимости охраны?

Sheet ТМЦ в холодильнике
A1: Дополнительное заявление на страхование "Страхование имущества от несоблюдения (нарушения) температурного режима"
A3: 1. | B3: Выберите необходимый объем страхового покрытия: *
A5: 2. | B5: Характеристика холодильного сооружения.
B6: 2.1. Количество независимых холодильных контуров:
B7: 2.2. Количество холодильных камер (отсеков):
B8: 2.3. Объем морозильных камер (кв.м):
B9: 2.4. Общая площадь холодильных камер (куб.м):
B10: 2.5. Высота (м):
B11: 2.6. Температура в камерах:
B12: 2.7. Содержание СО2 (%):
B13: 2.8. Содержание О2 (%):
B14: 2.9. Относительная влажность воздуха (%):
B15: 2.10. Давление воздуха (атм):
B16: 2.11. Наличие резервных источников электроэнергии:
B17: 2.12. Количество электрических вводов на предприятие (в здание):
... B21: 2.16. Дата последней замены изоляции:
A22: 3. | B22: Характеристика холодильной установки.
B23: 3.1. Дата ввода в эксплуатацию:
B24: 3.2. Укажите, кто осуществляет технадзор:
B25: 3.3. Инспекции проводятся с нормативной периодичностью?
B26: 3.4. Текущий ремонт проводится с нормативной периодичностью?
B27: 3.5. Кто проводит текущий ремонт?
B28: 3.6. Данная холодильная установка является собственностью?
B29: 3.7. Период времени в соответствии с технической документацией, в течение которого холодильная установка может сохранять заданный температурный режим при отключении электропитания или ее непредвиденной поломке, в часах:
A30: 4. | B30: Характеристика систем контроля и сигнализации.
B31: 4.1. Число и тип датчиков (температуры, влажности, СО2, СО, давления) в каждой камере:
B32: 4.2. Интервалы контроля, в часах:
B33: 4.3. Имеются ли сигнализаторы?
A34: 5. | B34: Резервные холодильные сооружения (наличие, адрес, какой % товара может быть перемещен).
B35: 5.1. Наличие:
B36: 5.2. Адрес:
B37: 5.3. Какой % товара может быть перемещен?

Sheet Ювелирные изделия и меха
A1: Дополнительное заявление на страхование "Ювелирные изделия, драгоценные камни и металлы, меха"
A3: 1. | B3: 1.1. Максимальная стоимость единицы ювелирных изделий, драгоценных камней и металлов (в рублях), мехов (если более 300 т.р. – приложить документы):
B4: 1.2. При наличии ЧОПа – указать реквизиты и приложить копию договора охраны:
B5: 1.3. Наличие исправной автоматической охранной сигнализации с выводом на пульт охраны (МВД, ЧОП и т.п.):
B6: 1.4. Наличие датчиков на все стекла и двери, а также на движение внутри помещения:
B7: 1.5. Остекление торговых витрин противоударное и без свободного доступа к изделиям со стороны покупателей и третьих лиц?
B8: 1.6. Площадь (объем) помещений, контролируемая извещателями:
B9: 1.7. Дверные проёмы, люки, ворота блокируются на «открывание» и «пролом»?
B10: 1.8. Остекленные конструкции блокируются на «открывание» и разрушение стекла?
B11: 1.9. Металлические двери, ворота блокируются на «открывание» и ударное воздействие?
B12: 1.10. Некапитальные стены, потолки и места ввода коммуникаций блокируются на «пролом»?
B13: 1.11. Капитальные стены, вентиляционные короба блокируются на разрушение и удар. Воздействие?
B14: 1.12. При отключении сетевого электропитания работоспособность ПКП (приемно-контрольный прибор) и извещателей обеспечена автономным питанием на 8 часов?
B15: 1.13. Во внерабочее время ценности убираются в сейф в сейфовую комнату?
... B17: 1.15. Сейф/сейфовая комната соответствует классу устойчивости к взлому не ниже 2?

Sheet перечень
A1: Номер | B1: Отрасль | C1: Суботрасль | G1: Авто-мотосалоны, авто-мотосервисы, автоломбарды и автодилеры | K1: Автозапчасти, автомобили, машиностроение
A2: 1 | B2: Текстильная промышленность, производство одежды, обуви | C2: Текстильная промышленность, производство одежды, обуви | G2: АЗС, ГАЗС, электрические заправки | K2: Алкогольная продукция
A3: 2.1. | B3: Лесная, деревообрабатывающая и целлюлозно-бумажная промышленность | C3: Заготовка и обработка древесины | G3: Горно-металлургические предприятия | K3: Аудио-, видеотехника, электромузыкальные инструменты, оргтехника и т.п., за исключением мобильных устройств, средств связи, фото и киноаппаратуры, оптики, часов
A4: 2.2. | B4: Лесная, деревообрабатывающая и целлюлозно-бумажная промышленность | C4: Производство изделий из древесины | G4: Гостиницы, дома отдыха, туристические базы | K4: Безалкогольные напитки
A5: 2.3. | B5: Лесная, деревообрабатывающая и целлюлозно-бумажная промышленность | C5: Целлюлозно-бумажные комбинаты | G5: Добыча полезных ископаемых (кроме нефти, газа) | K5: Бытовая химия (стиральные порошки, чистящие и моющие средства, удобрения, химикаты и т.п.)
A6: 3.1. | B6: Производство строительных материалов | C6: Производство цемента | G6: Жилая недвижимость, ТСЖ | K6: Взрывчатые и легковоспламеняющиеся жидкие вещества
A7: 3.2. | B7: Производство строительных материалов | C7: Производство стекла | G7: Жилищно-коммунальное хозяйство | K7: Галантерея (металлическая, пластмассовая и кожгалантерея, бижутерия, швейная фурнитура и т.п.)
A8: 3.3. | B8: Производство строительных материалов | C8: Производство кирпича, плитки, огнеупоров | G8: Лесная, деревообрабатывающая и целлюлозно-бумажная промышленность | K8: Имущество, не входящее в указанные группы
A9: 3.4. | B9: Производство строительных материалов | C9: Производство асфальта, битума | G9: Машиностроение и приборостроение | K9: Книги, журналы, другая полиграфическая продукция
A10: 3.5. | B10: Производство строительных материалов | C10: Производство прочих стройматериалов | G10: Медицинские учреждения (больницы, поликлиники, санатории) | K10: Мебель
A11: 4.1. | B11: Добыча полезных ископаемых (кроме нефти, газа) | C11: Добыча открытым способом (карьеры, разрезы) полезных ископаемых, минералов и сырья | G11: Научно-исследовательские лаборатории и т.п. | K11: Металлопрокат и прочая продукция металлургических заводов и комбинатов
A12: 4.2. | B12: Добыча полезных ископаемых (кроме нефти, газа) | C12: Добыча закрытым способом (шахты, рудники) полезных ископаемых, минералов и сырья, кроме угля | G12: Нефтяная/газовая промышленность | K12: Мобильные устройства (сотовые телефоны и т.п.), средства связи (телефонные аппараты, автоответчики, факсы и т.п.)
A13: 4.3. | B13: Добыча полезных ископаемых (кроме нефти, газа) | C13: Добыча угля закрытым способом (шахты, рудники) | G13: Объекты культуры, искусства, развлечений | K13: Нефасованный чай, кофе (категория выбирается в том случае, если доля нефасованного чая или кофе составляет более 50% от общей страховой суммы ТМЦ по территории страхования)
A14: 5.1. | B14: Горно-металлургические предприятия | C14: Металлургические комбинаты и заводы | G14: Объекты образования | K14: Одежда, головные уборы из натуральной кожи и натурального меха
... A28: 9.3. | B28: Электроэнергетика | C28: Атомные электростанции (АЭС) | G28: Химическая и нефтехимическая промышленность | K28: Ювелирные изделия
A29: 9.4. | B29: Электроэнергетика | C29: Передача (распределение) электроэнергии (электрические сети, подстанции) | G29: Хранение и обработка информации, ЦОД, телекоммуникации и связь
A30: 9.5. | B30: Электроэнергетика | C30: Возобновляемая энергетика (солнечные, ветровые, приливные, геотермальные и т.п. электростанции) | G30: Электроэнергетика
A31: 10.1. | B31: Пищевая промышленность | C31: Производство продуктов питания, безалкогольных напитков
A32: 10.2. | B32: Пищевая промышленность | C32: Производство сахара
A33: 10.3. | B33: Пищевая промышленность | C33: Масло-жировые комбинаты
A34: 10.4. | B34: Пищевая промышленность | C34: Производство алкогольных напитков
A35: 11 | B35: Прочие промышленные предприятия (обязательно указание) | C35: Прочие промышленные предприятия (обязательно указание)
A36: 1.1. | B36: Офисная недвижимость, адм. здания | C36: Коммерческого назначения
A37: 1.2. | B37: Офисная недвижимость, адм. здания | C37: Для государственных нужд
A38: 2.1. | B38: Торговля, торговая и торгово-развлекательная недвижимость | C38: Многофункциональная торговая недвижимость
A39: 2.2. | B39: Торговля, торговая и торгово-развлекательная недвижимость | C39: Предприятия торговли (за исключением антикварных салонов и ломбардов)
A40: 2.3. | B40: Торговля, торговая и торгово-развлекательная недвижимость | C40: Ломбарды, аукционные дома, антикварные салоны
A41: 3 | B41: Складская деятельность, логистика | C41: Складская деятельность, логистика
A42: 4 | B42: Авто-мотосалоны, авто-мотосервисы, автоломбарды и автодилеры | C42: Авто-мотосалоны, авто-мотосервисы, автоломбарды и автодилеры
A43: 5 | B43: Рестораны, кафе, бары, предприятия общественного питания | C43: Рестораны, кафе, бары, предприятия общественного питания
A44: 6 | B44: Гостиницы, дома отдыха, туристические базы | C44: Гостиницы, дома отдыха, туристические базы
A45: 7.1. | B45: Спортивные и оздоровительные объекты | C45: Стадионы, бассейны, фитнес-клубы, спортзалы
A46: 7.2. | B46: Спортивные и оздоровительные объекты | C46: Горнолыжные курорты / объекты
A47: 8 | B47: Медицинские учреждения (больницы, поликлиники, санатории) | C47: Медицинские учреждения (больницы, поликлиники, санатории)
A48: 9 | B48: Объекты образования | C48: Объекты образования
A49: 10 | B49: Научно-исследовательские лаборатории и т.п. | C49: Научно-исследовательские лаборатории и т.п.
A50: 11.1. | B50: Объекты культуры, искусства, развлечений | C50: Аттракционы, парки развлечений
A51: 11.2. | B51: Объекты культуры, искусства, развлечений | C51: Кинотеатры, театры, концертные залы, цирк, развлекательные комплексы
A52: 11.3. | B52: Объекты культуры, искусства, развлечений | C52: Музеи, выставки, галереи
A53: 11.4. | B53: Объекты культуры, искусства, развлечений | C53: Ночные клубы, дискотеки, казино
A54: 12 | B54: Социально-бытовое обслуживание населения | C54: Социально-бытовое обслуживание населения
A55: 13 | B55: Жилая недвижимость, ТСЖ | C55: Жилая недвижимость, ТСЖ
A56: 14 | B56: Операторы наружной рекламы | C56: Операторы наружной рекламы
A57: 15.1. | B57: Хранение и обработка информации, ЦОД, телекоммуникации и связь | C57: Беспроводная (сотовая) связь
A58: 15.2. | B58: Хранение и обработка информации, ЦОД, телекоммуникации и связь | C58: Стационарная связь, телекоммуникации и т.п.
A59: 15.3. | B59: Хранение и обработка информации, ЦОД, телекоммуникации и связь | C59: ЦОД, хранение и обработка данных, интернет компании, разработчики программного обеспечения
A60: 16.1. | B60: Транспортная инфраструктура | C60: Морские и речные порты
A61: 16.2. | B61: Транспортная инфраструктура | C61: Аэропорты
A62: 16.3. | B62: Транспортная инфраструктура | C62: Железные дороги
A63: 16.4 | B63: Транспортная инфраструктура | C63: Автомобильные дороги
A64: 17 | B64: АЗС, ГАЗС, электрические заправки | C64: АЗС, ГАЗС, электрические заправки
A65: 18.1. | B65: Жилищно-коммунальное хозяйство | C65: Котельные
A66: 18.2. | B66: Жилищно-коммунальное хозяйство | C66: Тепловые сети
A67: 18.3. | B67: Жилищно-коммунальное хозяйство | C67: Сети водоснабжения и канализации (водоканалы)
A68: 18.4. | B68: Жилищно-коммунальное хозяйство | C68: Сети газоснабжения
A69: 19 | B69: Прочие непромышленные объекты (обязательно указание) | C69: Прочие непромышленные объекты (обязательно указание)

Sheet Export
A1: Основной | F1: SYSDATE | G1: YEAR | I1: v.18_4
A2: № | B2: Раздел | C2: Пункт | D2: Значение | F2: =TODAY() -> 46255 | G2: =YEAR(F2) -> 2026
A3: 1 | B3: Информация о Страхователе | C3: Наименование Страхователя: | D3: =ИмяСтрахователя -> 0
A4: 2 | C4: Юридический адрес Страхователя: | D4: =Основной!E8 -> 0
A5: 3 | C5: ИНН Страхователя: | D5: =Основной!E9 -> 0
A6: 4 | C6: Контактное лицо Страхователя: | D6: =Основной!E10 -> 0
A7: 5 | C7: Телефон страхователя: | D7: =Основной!C11 -> 0
A8: 6 | C8: Email Страхователя | D8: =Основной!G11 -> 0
A9: 7 | B9: Информация о Выгодоприобретателе | C9: Наименование Выгодоприобретателя: | D9: =Основной!E14 -> ООО Сторук Воронеж
A10: 8 | C10: Юридический адрес Выгодоприобретателя: | D10: =Основной!E15 -> 0
A11: 9 | C11: ИНН Выгодоприобретателя: | D11: =Основной!E16 -> 3665806928
A12: 10 | C12: Договор-основание Выгодоприобретателя: | D12: =Основной!E17 -> 0
A13: 11 | C13: Номер Договора-основания: | D13: =Основной!E18 -> 0
A14: 12 | C14: Дата начала договора-основания: | D14: =Основной!I18 -> 0
A15: 13 | C15: Дата окончания договора-основания: | D15: =Основной!K18 -> 0
A16: 14 | C16: Контактная информация Выгодоприобретателя: | D16: =Основной!B20 -> 0
A17: 15 | B17: Период страхования | C17: Дата начала периода страхования: | D17: =Основной!G21 -> 0
A18: 16 | C18: Дата окончания периода страхования: | D18: =Основной!J21 -> 0
A19: 17 | B19: Территория страхования | C19: Страна | D19: =Основной!D23 -> 0
A20: 18 | C20: Индекс | D20: =Основной!J23 -> 0
A21: 19 | C21: Субъект / Область | D21: =Основной!D24 -> 0
A22: 20 | C22: Район | D22: =Основной!D25 -> 0
A23: 21 | C23: Населенный пункт | D23: =Основной!D26 -> 0
A24: 22 | C24: Улица | D24: =Основной!D27 -> 0
A25: 23 | C25: Дом | D25: =Основной!D28 -> 0
A26: 24 | C26: Корпус | D26: =Основной!G28 -> 0
A27: 25 | C27: Строение | D27: =Основной!J28 -> 0
A28: 26 | C28: Дополнительно | D28: =Основной!D29 -> 0
A29: 27 | B29: Общая хар-ка объектов страхования | C29: Основное назначение имущества | D29: =Основной!B32 -> 0
A30: 28 | C30: Категория имущества | D30: =Основной!B34 -> 0
A31: 29 | C31: Описание имущества | D31: =Основной!B36 -> 0
A32: 30 | C32: Валюта страхования | D32: 0
A33: 31 | C33: Иная валюта страхования | D33: =Основной!G38 -> 0
A34: 32 | C34: База стоимости | D34: 1
A35: 33 | C35: Иная база стоимости | D35: =Основной!D41 -> 0
A36: 34 | C36: НДС | D36: 0
A37: 35 | C37: Первый риск | D37: FALSE
A38: 36 | B38: Здание (конструктивные элементы, внутр. и внеш. отделка). | C38: Страховая сумма | D38: =Основной!H46 -> 0
A39: 37 | C39: Страховая стоимость | D39: =Основной!J46 -> 0
A40: 38 | B40: Здание (конструктивные элементы, инженерные коммуникации), исключая отделку. | C40: Страховая сумма | D40: =Основной!H47 -> 0
A41: 39 | C41: Страховая стоимость | D41: =Основной!J47 -> 0
A42: 40 | B42: Внешняя отделка здания или части здания, исключая дополнительные надстройки и оборудование. | C42: Страховая сумма | D42: =Основной!H48 -> 0
A43: 41 | C43: Страховая стоимость | D43: =Основной!J48 -> 0
A44: 42 | B44: Внутренняя отделка помещений. | C44: Страховая сумма | D44: =Основной!H49 -> 0
A45: 43 | C45: Страховая стоимость | D45: =Основной!J49 -> 0
A46: 44 | B46: Внешние сооружения и результаты работ по благоустройству территории страхования | C46: Страховая сумма | D46: =Основной!H50 -> 0
A47: 45 | C47: Страховая стоимость | D47: =Основной!J50 -> 0
A48: 46 | B48: Оконные стекла, витрины, стеклопакеты, стеклянные элементы | C48: Страховая сумма | D48: =Основной!H51 -> 0
A49: 47 | C49: Страховая стоимость | D49: =Основной!J51 -> 0
A50: 48 | B50: Различное оборудование, не являющееся конструктивной частью здания | C50: Страховая сумма | D50: =Основной!H52 -> 0
A51: 49 | C51: Страховая стоимость | D51: =Основной!J52 -> 0
A52: 50 | B52: Мебель, инструмент, инвентарь. | C52: Страховая сумма | D52: =Основной!H53 -> 0
A53: 51 | C53: Страховая стоимость | D53: =Основной!J53 -> 0
A54: 52 | B54: Товарные запасы готовой продукции | C54: Основная категория ТМЦ | D54: =Основной!B55 -> 0
A55: 53 | C55: Краткая характеристика ТМЦ | D55: =Основной!B57 -> 0
A56: 54 | C56: Страховая сумма | D56: =Основной!H55 -> 0
A57: 55 | C57: Стоимость максимального остатка ТМЦ | D57: =Основной!J55 -> 0
A58: 56 | B58: Наличные деньги | C58: Страховая сумма | D58: =Основной!H58 -> 0
A59: 57 | B59: Иное имущество | C59: Описание иного имущества | D59: =Основной!C59 -> 0
A60: 58 | C60: Страховая сумма | D60: =Основной!H59 -> 0
A61: 59 | C61: Страховая стоимость | D61: =Основной!J59 -> 0
A62: 60 | B62: Дополнительные расходы | C62: Нужны ли дополнительные расходы | D62: =IF(SUM(D63:D72)>0,1,0) -> 0
A63: 61 | C63: Дополнительные расходы по слому строений, расчистке территории, вывозу мусора. | D63: =Основной!J63 -> 0
A64: 62 | C64: Расходы, которые необходимо произвести в процессе восстановления застрахованного имущества или монтажа нового имущества, для того, чтобы демонтировать, переместить или защитить другое имущество (расходы на удаление и защиту). | D64: =Основной!J64 -> 0
A65: 63 | C65: Дополнительные расходы на оплату работ по ремонту поврежденного имущества в сверхурочное время, ночное время, в официальные праздники и выходные дни, а также транспортные расходы, вызванные срочностью проведения ремонтных работ. | D65: =Основной!J65 -> 0
A66: 64 | C66: Расходы по выяснению обстоятельств страхового события, расходы на сюрвейеров, экспертов и т.п. | D66: =Основной!J66 -> 0
A67: 65 | C67: Расходы на оплату услуг бухгалтеров, архитекторов, проектировщиков, аудиторов, инженеров и иных экспертов в объеме, необходимом для восстановления погибшего или поврежденного Застрахованного имущества. | D67: =Основной!J67 -> 0
A68: 66 | C68: Расходы, вызванные увеличением стоимости строительства (восстановительные работы после страхового случая) в связи с изменением строительных и иных норм и правил. | D68: =Основной!J68 -> 0
A69: 67 | C69: Расходы на восстановление планов, чертежей, договоров, бухгалтерских записей и утраченных или поврежденных электронных данных (включая данные на магнитных носителях при условии их дублирования), за исключением ценности содержащейся в документах и электронных данных информации. | D69: =Основной!J69 -> 0
A70: 68 | C70: Расходы на временный переезд на период восстановительных работ: расходы по вывозу (перемещению) имущества из поврежденного строения; расходы, связанные с передачей имущества на временное хранение; расходы на оборудование временно занимаемых помещений и арендную плату за их использование и т.д. | D70: =Основной!J70 -> 0
A71: 69 | C71: Иные расходы - характеристика | D71: =Основной!D71 -> 0
A72: 70 | C72: Иные расходы лимит возмещения | D72: =Основной!J71 -> 0
A73: 71 | B73: Основное страховое покрытие | C73: Вид покрытия (поименованные/все риски) | D73: 0
A74: 72 | C74: Пожар, воздействие продуктов горения (в том числе дыма), удар молнии, а также взрыв газа, употребляемого в бытовых целях | D74: TRUE
A75: 73 | C75: Стихийные бедствия | D75: TRUE
A76: 74 | C76: Повреждение застрахованного имущества водой из водопроводных, канализационных, отопительных систем, систем пожаротушения и кондиционирования | D76: TRUE
A77: 75 | C77: Взрыв паровых котлов, газохранилищ, газопроводов, машин, аппаратов и других аналогичных устройств | D77: TRUE
A78: 76 | C78: Злоумышленные действия третьих лиц | D78: TRUE
A79: 77 | C79: Кража с незаконным проникновением, грабеж, разбой | D79: FALSE
A80: 78 | C80: Наезд наземных транспортных средств | D80: FALSE
A81: 79 | C81: Падение на застрахованное имущество пилотируемых летающих объектов или их обломков | D81: TRUE
A82: 80 | C82: Бой оконных стекол, зеркал и витрин | D82: FALSE
A83: 81 | B83: Дополнительные риски | C83: Забастовки, народные волнения, массовые беспорядки | D83: FALSE
A84: 82 | C84: Забастовки, народные волнения, массовые беспорядки - Лимит возмещения | D84: =Основной!J76 -> 0
A85: 83 | C85: Терроризм | D85: FALSE
A86: 84 | C86: Терроризм - Лимит возмещения | D86: =Основной!J77 -> 0
A87: 85 | B87: Рискозащищенность по территории страхования | C87: Функциональное назначение здания | D87: =Основной!F79 -> 0
A88: 86 | C88: Занимаемый этаж | D88: =Основной!K79 -> 1-2
A89: 87 | C89: Помещение в собственности или арендуемое | D89: 2
A90: 88 | C90: Год постройки или последнего капремонта | D90: =Основной!H81 -> 0
A91: 89 | C91: Общая площадь здания (кв.м) | D91: =Основной!E82 -> 0
A92: 90 | C92: Занимаемая площадь (кв.м) | D92: =Основной!J82 -> 0
A93: 91 | C93: Здание: отдельностоящее или примыкающее | D93: 1
A94: 92 | C94: Окончены ли строительные/ремонтные/отделочные работы | D94: 1
A95: 93 | C95: Укажите строящиеся объекты и/или помещения в которых ведутся работы | D95: =Основной!D85 -> 0
A96: 94 | C96: Огне- и/или взрывоопасные вещества, технологии | D96: 1
A97: 95 | C97: Краткая характеристика веществ и технологий | D97: =Основной!D87 -> 0
A98: 96 | C98: Баня/сауна | D98: 2
A99: 97 | C99: Стены | D99: 2
A100: 98 | C100: Стены иные (укажите) | D100: =Основной!F91 -> 0
...
